api_test_ez/VERSION
api_test_ez/__init__.py
api_test_ez/cmd.py
api_test_ez/core/__init__.py
api_test_ez/core/case/__init__.py
api_test_ez/core/case/errors.py
api_test_ez/core/case/frame/__init__.py
api_test_ez/core/case/frame/frame_case_loader.py
api_test_ez/core/case/frame/frame_pytest.py
api_test_ez/core/case/frame/frame_unittest.py
api_test_ez/core/case/http/__init__.py
api_test_ez/core/case/http/request.py
api_test_ez/core/case/http/response.py
api_test_ez/core/report/__init__.py
api_test_ez/ez/__init__.py
api_test_ez/ez/config.py
api_test_ez/ez/case_builder/__init__.py
api_test_ez/ez/case_builder/fields.py
api_test_ez/ez/case_builder/schema.py
api_test_ez/ez/decorator/__init__.py
api_test_ez/ez/decorator/jsonbean.py
api_test_ez/ez/decorator/singleton.py
api_test_ez/ez/ez_marshmallow/__init__.py
api_test_ez/ez/ez_marshmallow/schema.py
api_test_ez/ez/http/__init__.py
api_test_ez/ez/http/http.py
api_test_ez/ez/log/__init__.py
api_test_ez/ez/log/log.py
api_test_ez/ez/serialize/__init__.py
api_test_ez/ez/serialize/errors.py
api_test_ez/ez/serialize/fields.py
api_test_ez/ez/serialize/models.py
api_test_ez/libs/HTMLTestRunner.py
api_test_ez/libs/__init__.py
api_test_ez/project/__init__.py
api_test_ez/project/configs/__init__.py
api_test_ez/project/configs/default_configs.cfg
api_test_ez/project/settings/__init__.py
api_test_ez/project/settings/default_settings.py
ApiTestEz-1.0.36.1.dist-info/METADATA
ApiTestEz-1.0.36.1.dist-info/WHEEL
ApiTestEz-1.0.36.1.dist-info/entry_points.txt
ApiTestEz-1.0.36.1.dist-info/top_level.txt
ApiTestEz-1.0.36.1.dist-info/RECORD
