Metadata-Version: 2.1
Name: ApiTestEz
Version: 1.0.36.1
Summary: An easier api test framework.
Home-page: https://github.com/bruce4520196/ApiTestEz
Author: Bruce Cai
Maintainer: Bruce Cai
Maintainer-email: whiteghostcat@gmail.com
Classifier: Framework :: Scrapy
Classifier: Development Status :: 5 - Production/Stable
Classifier: Environment :: Console
Classifier: Intended Audience :: Developers
Classifier: Operating System :: OS Independent
Classifier: Programming Language :: Python
Classifier: Programming Language :: Python :: 3
Classifier: Programming Language :: Python :: 3.5
Classifier: Programming Language :: Python :: 3.6
Classifier: Programming Language :: Python :: 3.7
Classifier: Programming Language :: Python :: 3.8
Classifier: Programming Language :: Python :: 3.9
Classifier: Programming Language :: Python :: 3.10
Classifier: Topic :: Internet :: WWW/HTTP
Classifier: Topic :: Software Development :: Libraries :: Python Modules
Requires-Python: >=3.5
Requires-Dist: tablib==3.2.1
Requires-Dist: ddt~=1.5.0
Requires-Dist: urllib3~=1.26.20
Requires-Dist: requests~=2.32.4
Requires-Dist: pytest~=7.1.2
Requires-Dist: openpyxl==3.0.10
Requires-Dist: BeautifulReport~=0.1.3
Requires-Dist: marshmallow~=3.16.0
